{
  "products": [
    {
      "id": 7,
      "name": "Vitamin C Serum",
      "category": "health",
      "image": "https://via.placeholder.com/300x240?text=Vitamin+C",
      "desc": "Visible results in 30 days. Stable formula.",
      "orig": 58,
      "curr": 42,
      "link": "https://amazon.com/dp/ASIN?tag=YOUR-TAG-HERE"
    },
    {
      "id": 8,
      "name": "Mighty Patch Acne Patches",
      "category": "health",
      "image": "https://via.placeholder.com/300x240?text=Mighty+Patch",
      "desc": "#1 seller. Flattens blemishes overnight.",
      "orig": 16,
      "curr": 11,
      "link": "https://amazon.com/dp/ASIN?tag=YOUR-TAG-HERE"
    },
    {
      "id": 9,
      "name": "Magnesium Glycinate",
      "category": "health",
      "image": "https://via.placeholder.com/300x240?text=Magnesium",
      "desc": "Better sleep within a week. No jitters.",
      "orig": 25,
      "curr": 18,
      "link": "https://amazon.com/dp/ASIN?tag=YOUR-TAG-HERE"
    },
    {
      "id": 10,
      "name": "Athletic Greens AG1",
      "category": "health",
      "image": "https://via.placeholder.com/300x240?text=Athletic+Greens",
      "desc": "75+ micronutrients. Energy, recovery, immunity.",
      "orig": 99,
      "curr": 79,
      "link": "https://amazon.com/dp/ASIN?tag=YOUR-TAG-HERE"
    },
    {
      "id": 11,
      "name": "Sleep Support Stack",
      "category": "health",
      "image": "https://via.placeholder.com/300x240?text=Sleep+Support",
      "desc": "Magnesium + Melatonin. Night time formula.",
      "orig": 32,
      "curr": 24,
      "link": "https://amazon.com/dp/ASIN?tag=YOUR-TAG-HERE"
    },
    {
      "id": 12,
      "name": "Face Moisturizer Premium",
      "category": "health",
      "image": "https://via.placeholder.com/300x240?text=Moisturizer",
      "desc": "Lightweight, fast absorb. Glowing skin in 5 days.",
      "orig": 68,
      "curr": 53,
      "link": "https://amazon.com/dp/ASIN?tag=YOUR-TAG-HERE"
    },
    {
      "id": 13,
      "name": "TERRO Ant Bait",
      "category": "home",
      "image": "https://via.placeholder.com/300x240?text=TERRO",
      "desc": "Eliminates entire colony. Household staple.",
      "orig": 12,
      "curr": 8,
      "link": "https://amazon.com/dp/ASIN?tag=YOUR-TAG-HERE"
    },
    {
      "id": 14,
      "name": "Mosquito Dunks",
      "category": "home",
      "image": "https://via.placeholder.com/300x240?text=Mosquito+Dunks",
      "desc": "Safe for pets & wildlife. Seasonal essential.",
      "orig": 20,
      "curr": 14,
      "link": "https://amazon.com/dp/ASIN?tag=YOUR-TAG-HERE"
    },
    {
      "id": 15,
      "name": "Zevo Insect Trap",
      "category": "home",
      "image": "https://via.placeholder.com/300x240?text=Zevo",
      "desc": "No sprays, smell, or mess. Set and forget.",
      "orig": 35,
      "curr": 26,
      "link": "https://amazon.com/dp/ASIN?tag=YOUR-TAG-HERE"
    },
    {
      "id": 16,
      "name": "Air Purifier Pro",
      "category": "home",
      "image": "https://via.placeholder.com/300x240?text=Air+Purifier",
      "desc": "True HEPA. Covers 400 sq ft. Ultra-quiet.",
      "orig": 549,
      "curr": 449,
      "link": "https://amazon.com/dp/ASIN?tag=YOUR-TAG-HERE"
    },
    {
      "id": 17,
      "name": "Litter-Robot 4",
      "category": "pet",
      "image": "https://via.placeholder.com/300x240?text=Litter-Robot",
      "desc": "Self-cleans. Gold standard for multi-cat homes.",
      "orig": 499,
      "curr": 399,
      "link": "https://amazon.com/dp/ASIN?tag=YOUR-TAG-HERE"
    },
    {
      "id": 18,
      "name": "Furbo Dog Camera",
      "category": "pet",
      "image": "https://via.placeholder.com/300x240?text=Furbo",
      "desc": "360° view, two-way audio, treat tossing.",
      "orig": 199,
      "curr": 149,
      "link": "https://amazon.com/dp/ASIN?tag=YOUR-TAG-HERE"
    },
    {
      "id": 19,
      "name": "Farmer's Dog Meals",
      "category": "pet",
      "image": "https://via.placeholder.com/300x240?text=Farmers+Dog",
      "desc": "Vet-formulated. Real ingredients. Health visible in weeks.",
      "orig": 70,
      "curr": 55,
      "link": "https://amazon.com/dp/ASIN?tag=YOUR-TAG-HERE"
    },
    {
      "id": 20,
      "name": "Veken Water Fountain",
      "category": "pet",
      "image": "https://via.placeholder.com/300x240?text=Veken",
      "desc": "Filtered flowing water keeps pets engaged.",
      "orig": 48,
      "curr": 36,
      "link": "https://amazon.com/dp/ASIN?tag=YOUR-TAG-HERE"
    },
    {
      "id": 21,
      "name": "Full Moon Chicken Jerky",
      "category": "pet",
      "image": "https://via.placeholder.com/300x240?text=Full+Moon",
      "desc": "Human-grade, single ingredient, USA-made.",
      "orig": 24,
      "curr": 18,
      "link": "https://amazon.com/dp/ASIN?tag=YOUR-TAG-HERE"
    },
    {
      "id": 22,
      "name": "Greenies Dental Treats",
      "category": "pet",
      "image": "https://via.placeholder.com/300x240?text=Greenies",
      "desc": "Vet-recommended. Cleans teeth while they enjoy.",
      "orig": 35,
      "curr": 28,
      "link": "https://amazon.com/dp/ASIN?tag=YOUR-TAG-HERE"
    },
    {
      "id": 23,
      "name": "Nortic Track L series",
      "category": "fitness",
      "image": "https://imgur.com/a/0kdVdEK",
      "desc": "NordicTrack T Series 6.5S Folding Treadmill — Get Fit Without Leaving Home\n\nThis is the treadmill that actually gets used. Foldable enough for a spare bedroom, powerful enough for serious training — the NordicTrack T Series 6.5S hits the sweet spot between performance and practicality.\n\nWhat you get:\n\n• Speeds up to 10 MPH — walk, jog, or run\n\n• 0–10% OneTouch incline for serious calorie burn\n\n• FlexSelect cushioning to protect your joints\n\n• 300 lb weight capacity\n\n• 5” LCD display + device shelf\n\n• Bluetooth heart-rate compatible\n\n• EasyLift folding design for compact storage\n\nAmazon’s Choice | 4.5 Stars | Best Seller in Home Treadmills\n\n🔥 Limited Time: $624 — 22% off the regular $799 price\n\n\n\n",
      "orig": 799,
      "curr": 624,
      "link": "https://amzn.to/4vsQAj2"
    },
    {
      "id": 24,
      "name": "NordicTrack T Series",
      "category": "fitness",
      "image": "https://imgur.com/a/0kdVdEK",
      "desc": "This is the treadmill that actually gets used. Foldable enough for a spare bedroom, powerful enough for serious training — the NordicTrack T Series 6.5S hits the sweet spot between performance and practicality.\n\n\n\nWhat you get:\n\n\n\n• Speeds up to 10 MPH — walk, jog, or run\n\n• 0–10% OneTouch incline for serious calorie burn\n\n• FlexSelect cushioning to protect your joints\n\n• 300 lb weight capacity\n\n• 5” LCD display + device shelf\n\n• Bluetooth heart-rate compatible\n\n• EasyLift folding design for compact storage\n\nAmazon’s Choice | 4.5 Stars | Best Seller in Home Treadmills",
      "orig": 799,
      "curr": 624,
      "link": "https://amzn.to/4vsQAj2"
    }
  ]
}
